{
  "university": "РУТ (МИИТ)",
  "group": "УПМ-211",
  "updatedAt": "2026-06-11T02:37:19+03:00",
  "events": [
    {
      "date": "2026-06-15",
      "weekday": "Понедельник",
      "time": "09:00 — 10:00",
      "kind": "Консультация",
      "subject": "Дифференциальные уравнения",
      "teacher": "Братусь А.С",
      "room": "1313",
      "isPast": false
    },
    {
      "date": "2026-06-16",
      "weekday": "Вторник",
      "time": "11:00 — 18:00",
      "kind": "Экзамен",
      "subject": "Дифференциальные уравнения",
      "teacher": "Братусь А.С",
      "room": "1313",
      "isPast": false
    },
    {
      "date": "2026-06-19",
      "weekday": "Пятница",
      "time": "09:00 — 10:00",
      "kind": "Консультация",
      "subject": "Математический анализ",
      "teacher": "Братусь А.С",
      "room": "1313",
      "isPast": false
    },
    {
      "date": "2026-06-22",
      "weekday": "Понедельник",
      "time": "11:00 — 18:00",
      "kind": "Экзамен",
      "subject": "Математический анализ",
      "teacher": "Братусь А.С",
      "room": "1313",
      "isPast": false
    },
    {
      "date": "2026-06-25",
      "weekday": "Четверг",
      "time": "09:00 — 10:00",
      "kind": "Консультация",
      "subject": "Теория вероятностей и математическая статистика",
      "teacher": "Турцынский М.К",
      "room": "1307",
      "isPast": false
    },
    {
      "date": "2026-06-26",
      "weekday": "Пятница",
      "time": "11:00 — 18:00",
      "kind": "Экзамен",
      "subject": "Теория вероятностей и математическая статистика",
      "teacher": "Турцынский М.К",
      "room": "1307",
      "isPast": false
    }
  ]
}