{
  "university": "РУТ (МИИТ)",
  "group": "ШАД-311",
  "updatedAt": "2026-06-11T02:25:03+03:00",
  "events": [
    {
      "date": "2026-06-15",
      "weekday": "Понедельник",
      "time": "09:00 — 10:00",
      "kind": "Консультация",
      "subject": "Программирование на Java",
      "teacher": "Глускер А.И",
      "room": "8507",
      "isPast": false
    },
    {
      "date": "2026-06-16",
      "weekday": "Вторник",
      "time": "10:00 — 15:00",
      "kind": "Экзамен",
      "subject": "Программирование на Java",
      "teacher": "Глускер А.И",
      "room": "8507",
      "isPast": false
    },
    {
      "date": "2026-06-19",
      "weekday": "Пятница",
      "time": "09:00 — 10:00",
      "kind": "Консультация",
      "subject": "История России",
      "teacher": "Кочетков Е.Е",
      "room": "8410",
      "isPast": false
    },
    {
      "date": "2026-06-20",
      "weekday": "Суббота",
      "time": "10:00 — 15:00",
      "kind": "Экзамен",
      "subject": "История России",
      "teacher": "Кочетков Е.Е",
      "room": "8410",
      "isPast": false
    },
    {
      "date": "2026-06-23",
      "weekday": "Вторник",
      "time": "09:00 — 10:00",
      "kind": "Консультация",
      "subject": "Основы теории искусственного интеллекта",
      "teacher": "Зиганшин Р.Ф",
      "room": "8407",
      "isPast": false
    },
    {
      "date": "2026-06-24",
      "weekday": "Среда",
      "time": "10:00 — 15:00",
      "kind": "Экзамен",
      "subject": "Основы теории искусственного интеллекта",
      "teacher": "Зиганшин Р.Ф",
      "room": "8407",
      "isPast": false
    },
    {
      "date": "2026-06-27",
      "weekday": "Суббота",
      "time": "09:00 — 10:00",
      "kind": "Консультация",
      "subject": "Информационная безопасность",
      "teacher": "Губенко И.М",
      "room": "8407",
      "isPast": false
    },
    {
      "date": "2026-06-29",
      "weekday": "Понедельник",
      "time": "10:00 — 15:00",
      "kind": "Экзамен",
      "subject": "Информационная безопасность",
      "teacher": "Губенко И.М",
      "room": "8407",
      "isPast": false
    }
  ]
}