{
  "university": "РУТ (МИИТ)",
  "group": "ЮСИ-241",
  "updatedAt": "2026-06-11T02:43:53+03:00",
  "events": [
    {
      "date": "2026-06-16",
      "weekday": "Вторник",
      "time": "10:00 — 11:00",
      "kind": "Консультация",
      "subject": "Криминалистика",
      "teacher": "Шкоропат Е.А",
      "room": "6305а",
      "isPast": false
    },
    {
      "date": "2026-06-17",
      "weekday": "Среда",
      "time": "11:00 — 18:00",
      "kind": "Экзамен",
      "subject": "Криминалистика",
      "teacher": "Шкоропат Е.А",
      "room": "6305а",
      "isPast": false
    },
    {
      "date": "2026-06-24",
      "weekday": "Среда",
      "time": "10:00 — 11:00",
      "kind": "Консультация",
      "subject": "Административное право",
      "teacher": "Эфендиев Т.С",
      "room": "6310",
      "isPast": false
    },
    {
      "date": "2026-06-25",
      "weekday": "Четверг",
      "time": "11:00 — 18:00",
      "kind": "Экзамен",
      "subject": "Административное право",
      "teacher": "Эфендиев Т.С",
      "room": "6310",
      "isPast": false
    },
    {
      "date": "2026-06-29",
      "weekday": "Понедельник",
      "time": "10:00 — 11:00",
      "kind": "Консультация",
      "subject": "Уголовное право и уголовный процесс",
      "teacher": "Новиков В.А",
      "room": "6305в",
      "isPast": false
    },
    {
      "date": "2026-06-30",
      "weekday": "Вторник",
      "time": "11:00 — 18:00",
      "kind": "Экзамен",
      "subject": "Уголовное право и уголовный процесс",
      "teacher": "Новиков В.А",
      "room": "6305в",
      "isPast": false
    }
  ]
}