{
  "schemaVersion": 1,
  "universityId": "moscow-rut-miit",
  "university": "РУТ (МИИТ)",
  "groupId": "177602",
  "group": "ТМС-311",
  "updatedAt": "2026-06-12T20:09:16+03:00",
  "semester": {
    "startDate": "2026-06-01",
    "endDate": "2026-06-30",
    "firstWeekParity": "odd"
  },
  "events": [
    {
      "id": "moscow-rut-miit_177602_2026-06-15_eb6a46ee805a",
      "date": "2026-06-15",
      "weekday": "Понедельник",
      "weekdayNumber": 1,
      "time": "09:00 — 10:00",
      "startTime": "09:00",
      "endTime": "10:00",
      "kind": "Консультация",
      "category": "consultation",
      "subject": "Теория и расчет измерительных преобразователей и приборов",
      "teacher": "Дудин Борис Алексеевич",
      "room": "4427",
      "address": "",
      "groups": [],
      "subgroup": "",
      "note": "",
      "isOnline": false,
      "onlineUrl": "",
      "sourceType": 1,
      "sourceUrl": "https://www.miit.ru/timetable/177602?start=2026-06-01&type=1"
    },
    {
      "id": "moscow-rut-miit_177602_2026-06-16_eff570131be9",
      "date": "2026-06-16",
      "weekday": "Вторник",
      "weekdayNumber": 2,
      "time": "11:00 — 18:00",
      "startTime": "11:00",
      "endTime": "18:00",
      "kind": "Экзамен",
      "category": "exam",
      "subject": "Теория и расчет измерительных преобразователей и приборов",
      "teacher": "Дудин Борис Алексеевич",
      "room": "4427",
      "address": "",
      "groups": [],
      "subgroup": "",
      "note": "Экзамен",
      "isOnline": false,
      "onlineUrl": "",
      "sourceType": 1,
      "sourceUrl": "https://www.miit.ru/timetable/177602?start=2026-06-01&type=1"
    },
    {
      "id": "moscow-rut-miit_177602_2026-06-19_6a990db47298",
      "date": "2026-06-19",
      "weekday": "Пятница",
      "weekdayNumber": 5,
      "time": "09:00 — 10:00",
      "startTime": "09:00",
      "endTime": "10:00",
      "kind": "Консультация",
      "category": "consultation",
      "subject": "Организация и технология испытаний",
      "teacher": "Логин Виктор Викторович",
      "room": "2311",
      "address": "",
      "groups": [],
      "subgroup": "",
      "note": "",
      "isOnline": false,
      "onlineUrl": "",
      "sourceType": 1,
      "sourceUrl": "https://www.miit.ru/timetable/177602?start=2026-06-01&type=1"
    },
    {
      "id": "moscow-rut-miit_177602_2026-06-20_a19ae5458f97",
      "date": "2026-06-20",
      "weekday": "Суббота",
      "weekdayNumber": 6,
      "time": "11:00 — 18:00",
      "startTime": "11:00",
      "endTime": "18:00",
      "kind": "Экзамен",
      "category": "exam",
      "subject": "Организация и технология испытаний",
      "teacher": "Логин Виктор Викторович",
      "room": "2311",
      "address": "",
      "groups": [],
      "subgroup": "",
      "note": "Экзамен",
      "isOnline": false,
      "onlineUrl": "",
      "sourceType": 1,
      "sourceUrl": "https://www.miit.ru/timetable/177602?start=2026-06-01&type=1"
    },
    {
      "id": "moscow-rut-miit_177602_2026-06-25_ef57195f39f8",
      "date": "2026-06-25",
      "weekday": "Четверг",
      "weekdayNumber": 4,
      "time": "09:00 — 10:00",
      "startTime": "09:00",
      "endTime": "10:00",
      "kind": "Консультация",
      "category": "consultation",
      "subject": "Аккредитация объектов транспортного комплекса",
      "teacher": "Тарасова Алена Иосифовна",
      "room": "2306",
      "address": "",
      "groups": [],
      "subgroup": "",
      "note": "",
      "isOnline": false,
      "onlineUrl": "",
      "sourceType": 1,
      "sourceUrl": "https://www.miit.ru/timetable/177602?start=2026-06-01&type=1"
    },
    {
      "id": "moscow-rut-miit_177602_2026-06-26_14e79b62280e",
      "date": "2026-06-26",
      "weekday": "Пятница",
      "weekdayNumber": 5,
      "time": "11:00 — 18:00",
      "startTime": "11:00",
      "endTime": "18:00",
      "kind": "Экзамен",
      "category": "exam",
      "subject": "Аккредитация объектов транспортного комплекса",
      "teacher": "Тарасова Алена Иосифовна",
      "room": "2306",
      "address": "",
      "groups": [],
      "subgroup": "",
      "note": "Экзамен",
      "isOnline": false,
      "onlineUrl": "",
      "sourceType": 1,
      "sourceUrl": "https://www.miit.ru/timetable/177602?start=2026-06-01&type=1"
    }
  ],
  "lessons": {
    "odd": [],
    "even": []
  },
  "exceptions": [],
  "meta": {
    "source": "miit.ru",
    "parserVersion": "3.2-js-smart-safe",
    "timezone": "Europe/Moscow",
    "errors": []
  }
}