{
  "schemaVersion": 1,
  "universityId": "moscow-rut-miit",
  "university": "РУТ (МИИТ)",
  "groupId": "192970",
  "group": "ТКТ-532",
  "updatedAt": "2026-06-12T20:08:46+03:00",
  "semester": {
    "startDate": "2026-06-01",
    "endDate": "2026-06-30",
    "firstWeekParity": "odd"
  },
  "events": [
    {
      "id": "moscow-rut-miit_192970_2025-11-05_d541b780d0f4",
      "date": "2025-11-05",
      "weekday": "Среда",
      "weekdayNumber": 3,
      "time": "13:45 — 15:05",
      "startTime": "13:45",
      "endTime": "15:05",
      "kind": "Экзамен",
      "category": "exam",
      "subject": "Управление станками и станочными комплексами",
      "teacher": "Попова Татьяна Александровна",
      "room": "2126-2",
      "address": "",
      "groups": [],
      "subgroup": "",
      "note": "Экзамен",
      "isOnline": false,
      "onlineUrl": "",
      "sourceType": 1,
      "sourceUrl": "https://www.miit.ru/timetable/192970?start=2026-06-01&type=1"
    },
    {
      "id": "moscow-rut-miit_192970_2025-11-05_775be3be914b",
      "date": "2025-11-05",
      "weekday": "Среда",
      "weekdayNumber": 3,
      "time": "16:55 — 18:15",
      "startTime": "16:55",
      "endTime": "18:15",
      "kind": "Экзамен",
      "category": "exam",
      "subject": "Технология машиностроения",
      "teacher": "Фоля Татьяна Ивановна",
      "room": "2126-2",
      "address": "",
      "groups": [],
      "subgroup": "",
      "note": "Экзамен",
      "isOnline": false,
      "onlineUrl": "",
      "sourceType": 1,
      "sourceUrl": "https://www.miit.ru/timetable/192970?start=2026-06-01&type=1"
    },
    {
      "id": "moscow-rut-miit_192970_2025-11-06_052637ac3c78",
      "date": "2025-11-06",
      "weekday": "Четверг",
      "weekdayNumber": 4,
      "time": "13:45 — 15:05",
      "startTime": "13:45",
      "endTime": "15:05",
      "kind": "Экзамен",
      "category": "exam",
      "subject": "Оборудование машиностроительных производств",
      "teacher": "Комаров Юрий Юрьевич",
      "room": "2126",
      "address": "",
      "groups": [],
      "subgroup": "",
      "note": "Экзамен",
      "isOnline": false,
      "onlineUrl": "",
      "sourceType": 1,
      "sourceUrl": "https://www.miit.ru/timetable/192970?start=2026-06-01&type=1"
    }
  ],
  "lessons": {
    "odd": [
      {
        "id": "moscow-rut-miit__w1_7f8123263d76",
        "date": "",
        "weekday": "Понедельник",
        "weekdayNumber": 1,
        "time": "13:45 — 15:05",
        "startTime": "13:45",
        "endTime": "15:05",
        "kind": "Лекция",
        "category": "lesson",
        "subject": "Технологические процессы сборки",
        "teacher": "Попова Татьяна Александровна",
        "room": "2126-2",
        "address": "",
        "groups": [],
        "subgroup": "",
        "note": "Лк",
        "isOnline": false,
        "onlineUrl": "",
        "sourceType": 1,
        "sourceUrl": "https://www.miit.ru/timetable/192970?start=2026-06-01&type=1"
      },
      {
        "id": "moscow-rut-miit__w1_0342c8a64f2a",
        "date": "",
        "weekday": "Понедельник",
        "weekdayNumber": 1,
        "time": "15:20 — 16:40",
        "startTime": "15:20",
        "endTime": "16:40",
        "kind": "Лекция",
        "category": "lesson",
        "subject": "Технологические процессы сборки",
        "teacher": "Попова Татьяна Александровна",
        "room": "2126-2",
        "address": "",
        "groups": [],
        "subgroup": "",
        "note": "Лк",
        "isOnline": false,
        "onlineUrl": "",
        "sourceType": 1,
        "sourceUrl": "https://www.miit.ru/timetable/192970?start=2026-06-01&type=1"
      },
      {
        "id": "moscow-rut-miit__w1_f8c8b4d82aaf",
        "date": "",
        "weekday": "Понедельник",
        "weekdayNumber": 1,
        "time": "16:55 — 18:15",
        "startTime": "16:55",
        "endTime": "18:15",
        "kind": "Лекция",
        "category": "lesson",
        "subject": "Технологические процессы сборки",
        "teacher": "Попова Татьяна Александровна",
        "room": "2126-2",
        "address": "",
        "groups": [],
        "subgroup": "",
        "note": "Лк",
        "isOnline": false,
        "onlineUrl": "",
        "sourceType": 1,
        "sourceUrl": "https://www.miit.ru/timetable/192970?start=2026-06-01&type=1"
      },
      {
        "id": "moscow-rut-miit__w1_204e7e21751f",
        "date": "",
        "weekday": "Понедельник",
        "weekdayNumber": 1,
        "time": "18:30 — 19:50",
        "startTime": "18:30",
        "endTime": "19:50",
        "kind": "Лекция",
        "category": "lesson",
        "subject": "Технологические процессы сборки",
        "teacher": "Попова Татьяна Александровна",
        "room": "2126-2",
        "address": "",
        "groups": [],
        "subgroup": "",
        "note": "Лк",
        "isOnline": false,
        "onlineUrl": "",
        "sourceType": 1,
        "sourceUrl": "https://www.miit.ru/timetable/192970?start=2026-06-01&type=1"
      },
      {
        "id": "moscow-rut-miit__w1_877fb34b66bd",
        "date": "",
        "weekday": "Понедельник",
        "weekdayNumber": 1,
        "time": "20:00 — 21:20",
        "startTime": "20:00",
        "endTime": "21:20",
        "kind": "Лекция",
        "category": "lesson",
        "subject": "Технологические процессы сборки",
        "teacher": "Попова Татьяна Александровна",
        "room": "2126-2",
        "address": "",
        "groups": [],
        "subgroup": "",
        "note": "Лк",
        "isOnline": false,
        "onlineUrl": "",
        "sourceType": 1,
        "sourceUrl": "https://www.miit.ru/timetable/192970?start=2026-06-01&type=1"
      },
      {
        "id": "moscow-rut-miit__w2_53371cd354fd",
        "date": "",
        "weekday": "Вторник",
        "weekdayNumber": 2,
        "time": "13:45 — 15:05",
        "startTime": "13:45",
        "endTime": "15:05",
        "kind": "Практическое занятие",
        "category": "lesson",
        "subject": "Управление станками и станочными комплексами",
        "teacher": "Попова Татьяна Александровна",
        "room": "2126-2",
        "address": "",
        "groups": [],
        "subgroup": "",
        "note": "ПЗ",
        "isOnline": false,
        "onlineUrl": "",
        "sourceType": 1,
        "sourceUrl": "https://www.miit.ru/timetable/192970?start=2026-06-01&type=1"
      },
      {
        "id": "moscow-rut-miit__w2_db0e11ed4b55",
        "date": "",
        "weekday": "Вторник",
        "weekdayNumber": 2,
        "time": "15:20 — 16:40",
        "startTime": "15:20",
        "endTime": "16:40",
        "kind": "Практическое занятие",
        "category": "lesson",
        "subject": "Управление станками и станочными комплексами",
        "teacher": "Попова Татьяна Александровна",
        "room": "2126-2",
        "address": "",
        "groups": [],
        "subgroup": "",
        "note": "ПЗ",
        "isOnline": false,
        "onlineUrl": "",
        "sourceType": 1,
        "sourceUrl": "https://www.miit.ru/timetable/192970?start=2026-06-01&type=1"
      },
      {
        "id": "moscow-rut-miit__w2_4c956595d07f",
        "date": "",
        "weekday": "Вторник",
        "weekdayNumber": 2,
        "time": "16:55 — 18:15",
        "startTime": "16:55",
        "endTime": "18:15",
        "kind": "Практическое занятие",
        "category": "lesson",
        "subject": "Управление станками и станочными комплексами",
        "teacher": "Попова Татьяна Александровна",
        "room": "2126-2",
        "address": "",
        "groups": [],
        "subgroup": "",
        "note": "ПЗ",
        "isOnline": false,
        "onlineUrl": "",
        "sourceType": 1,
        "sourceUrl": "https://www.miit.ru/timetable/192970?start=2026-06-01&type=1"
      },
      {
        "id": "moscow-rut-miit__w2_55090accda88",
        "date": "",
        "weekday": "Вторник",
        "weekdayNumber": 2,
        "time": "18:30 — 19:50",
        "startTime": "18:30",
        "endTime": "19:50",
        "kind": "Практическое занятие",
        "category": "lesson",
        "subject": "Управление станками и станочными комплексами",
        "teacher": "Попова Татьяна Александровна",
        "room": "2126-2",
        "address": "",
        "groups": [],
        "subgroup": "",
        "note": "ПЗ",
        "isOnline": false,
        "onlineUrl": "",
        "sourceType": 1,
        "sourceUrl": "https://www.miit.ru/timetable/192970?start=2026-06-01&type=1"
      },
      {
        "id": "moscow-rut-miit__w2_146d877e9803",
        "date": "",
        "weekday": "Вторник",
        "weekdayNumber": 2,
        "time": "20:00 — 21:20",
        "startTime": "20:00",
        "endTime": "21:20",
        "kind": "Практическое занятие",
        "category": "lesson",
        "subject": "Управление станками и станочными комплексами",
        "teacher": "Попова Татьяна Александровна",
        "room": "2126-2",
        "address": "",
        "groups": [],
        "subgroup": "",
        "note": "ПЗ",
        "isOnline": false,
        "onlineUrl": "",
        "sourceType": 1,
        "sourceUrl": "https://www.miit.ru/timetable/192970?start=2026-06-01&type=1"
      },
      {
        "id": "moscow-rut-miit__w3_938568ca4e0e",
        "date": "",
        "weekday": "Среда",
        "weekdayNumber": 3,
        "time": "11:40 — 13:00",
        "startTime": "11:40",
        "endTime": "13:00",
        "kind": "Курсовая работа",
        "category": "lesson",
        "subject": "Управление станками и станочными комплексами",
        "teacher": "Попова Татьяна Александровна",
        "room": "2126-2",
        "address": "",
        "groups": [],
        "subgroup": "",
        "note": "КР",
        "isOnline": false,
        "onlineUrl": "",
        "sourceType": 1,
        "sourceUrl": "https://www.miit.ru/timetable/192970?start=2026-06-01&type=1"
      },
      {
        "id": "moscow-rut-miit__w3_589aef6bbbd5",
        "date": "",
        "weekday": "Среда",
        "weekdayNumber": 3,
        "time": "13:45 — 15:05",
        "startTime": "13:45",
        "endTime": "15:05",
        "kind": "Лекция",
        "category": "lesson",
        "subject": "Технологические процессы сборки",
        "teacher": "Попова Татьяна Александровна",
        "room": "2126-2",
        "address": "",
        "groups": [],
        "subgroup": "",
        "note": "Лк",
        "isOnline": false,
        "onlineUrl": "",
        "sourceType": 1,
        "sourceUrl": "https://www.miit.ru/timetable/192970?start=2026-06-01&type=1"
      },
      {
        "id": "moscow-rut-miit__w3_bf4bc480e671",
        "date": "",
        "weekday": "Среда",
        "weekdayNumber": 3,
        "time": "16:55 — 18:15",
        "startTime": "16:55",
        "endTime": "18:15",
        "kind": "Практическое занятие",
        "category": "lesson",
        "subject": "Технологические процессы сборки",
        "teacher": "Попова Татьяна Александровна",
        "room": "2126-2",
        "address": "",
        "groups": [],
        "subgroup": "",
        "note": "ПЗ",
        "isOnline": false,
        "onlineUrl": "",
        "sourceType": 1,
        "sourceUrl": "https://www.miit.ru/timetable/192970?start=2026-06-01&type=1"
      },
      {
        "id": "moscow-rut-miit__w3_91f31aa455cf",
        "date": "",
        "weekday": "Среда",
        "weekdayNumber": 3,
        "time": "18:30 — 19:50",
        "startTime": "18:30",
        "endTime": "19:50",
        "kind": "Практическое занятие",
        "category": "lesson",
        "subject": "Технологические процессы сборки",
        "teacher": "Попова Татьяна Александровна",
        "room": "2126-2",
        "address": "",
        "groups": [],
        "subgroup": "",
        "note": "ПЗ",
        "isOnline": false,
        "onlineUrl": "",
        "sourceType": 1,
        "sourceUrl": "https://www.miit.ru/timetable/192970?start=2026-06-01&type=1"
      },
      {
        "id": "moscow-rut-miit__w3_a819c85451aa",
        "date": "",
        "weekday": "Среда",
        "weekdayNumber": 3,
        "time": "20:00 — 21:20",
        "startTime": "20:00",
        "endTime": "21:20",
        "kind": "Практическое занятие",
        "category": "lesson",
        "subject": "Технологические процессы сборки",
        "teacher": "Попова Татьяна Александровна",
        "room": "2126-2",
        "address": "",
        "groups": [],
        "subgroup": "",
        "note": "ПЗ",
        "isOnline": false,
        "onlineUrl": "",
        "sourceType": 1,
        "sourceUrl": "https://www.miit.ru/timetable/192970?start=2026-06-01&type=1"
      },
      {
        "id": "moscow-rut-miit__w4_7eccb7a30ca0",
        "date": "",
        "weekday": "Четверг",
        "weekdayNumber": 4,
        "time": "13:45 — 15:05",
        "startTime": "13:45",
        "endTime": "15:05",
        "kind": "Практическое занятие",
        "category": "lesson",
        "subject": "Технологические процессы сборки",
        "teacher": "Попова Татьяна Александровна",
        "room": "2126-2",
        "address": "",
        "groups": [],
        "subgroup": "",
        "note": "ПЗ",
        "isOnline": false,
        "onlineUrl": "",
        "sourceType": 1,
        "sourceUrl": "https://www.miit.ru/timetable/192970?start=2026-06-01&type=1"
      },
      {
        "id": "moscow-rut-miit__w4_45a413a00632",
        "date": "",
        "weekday": "Четверг",
        "weekdayNumber": 4,
        "time": "15:20 — 16:40",
        "startTime": "15:20",
        "endTime": "16:40",
        "kind": "Практическое занятие",
        "category": "lesson",
        "subject": "Технологические процессы сборки",
        "teacher": "Попова Татьяна Александровна",
        "room": "2126-2",
        "address": "",
        "groups": [],
        "subgroup": "",
        "note": "ПЗ",
        "isOnline": false,
        "onlineUrl": "",
        "sourceType": 1,
        "sourceUrl": "https://www.miit.ru/timetable/192970?start=2026-06-01&type=1"
      },
      {
        "id": "moscow-rut-miit__w4_1d0e5835f5e8",
        "date": "",
        "weekday": "Четверг",
        "weekdayNumber": 4,
        "time": "16:55 — 18:15",
        "startTime": "16:55",
        "endTime": "18:15",
        "kind": "Практическое занятие",
        "category": "lesson",
        "subject": "Технологические процессы сборки",
        "teacher": "Попова Татьяна Александровна",
        "room": "2126-2",
        "address": "",
        "groups": [],
        "subgroup": "",
        "note": "ПЗ",
        "isOnline": false,
        "onlineUrl": "",
        "sourceType": 1,
        "sourceUrl": "https://www.miit.ru/timetable/192970?start=2026-06-01&type=1"
      },
      {
        "id": "moscow-rut-miit__w4_71de8386240a",
        "date": "",
        "weekday": "Четверг",
        "weekdayNumber": 4,
        "time": "18:30 — 19:50",
        "startTime": "18:30",
        "endTime": "19:50",
        "kind": "Практическое занятие",
        "category": "lesson",
        "subject": "Технологические процессы сборки",
        "teacher": "Попова Татьяна Александровна",
        "room": "2126-2",
        "address": "",
        "groups": [],
        "subgroup": "",
        "note": "ПЗ",
        "isOnline": false,
        "onlineUrl": "",
        "sourceType": 1,
        "sourceUrl": "https://www.miit.ru/timetable/192970?start=2026-06-01&type=1"
      },
      {
        "id": "moscow-rut-miit__w4_9c5972dcb7ed",
        "date": "",
        "weekday": "Четверг",
        "weekdayNumber": 4,
        "time": "20:00 — 21:20",
        "startTime": "20:00",
        "endTime": "21:20",
        "kind": "Практическое занятие",
        "category": "lesson",
        "subject": "Технологические процессы сборки",
        "teacher": "Попова Татьяна Александровна",
        "room": "2126-2",
        "address": "",
        "groups": [],
        "subgroup": "",
        "note": "ПЗ",
        "isOnline": false,
        "onlineUrl": "",
        "sourceType": 1,
        "sourceUrl": "https://www.miit.ru/timetable/192970?start=2026-06-01&type=1"
      }
    ],
    "even": [
      {
        "id": "moscow-rut-miit__w1_58da1dab8177",
        "date": "",
        "weekday": "Понедельник",
        "weekdayNumber": 1,
        "time": "13:45 — 15:05",
        "startTime": "13:45",
        "endTime": "15:05",
        "kind": "Лекция",
        "category": "lesson",
        "subject": "Оборудование машиностроительных производств",
        "teacher": "Комаров Юрий Юрьевич",
        "room": "2126-2",
        "address": "",
        "groups": [],
        "subgroup": "",
        "note": "Лк",
        "isOnline": false,
        "onlineUrl": "",
        "sourceType": 1,
        "sourceUrl": "https://www.miit.ru/timetable/192970?start=2026-06-01&type=1"
      },
      {
        "id": "moscow-rut-miit__w1_a5bbd846bf8c",
        "date": "",
        "weekday": "Понедельник",
        "weekdayNumber": 1,
        "time": "13:45 — 15:05",
        "startTime": "13:45",
        "endTime": "15:05",
        "kind": "Лекция",
        "category": "lesson",
        "subject": "Технология машиностроения",
        "teacher": "Фоля Татьяна Ивановна",
        "room": "2126-2",
        "address": "",
        "groups": [],
        "subgroup": "",
        "note": "Лк",
        "isOnline": false,
        "onlineUrl": "",
        "sourceType": 1,
        "sourceUrl": "https://www.miit.ru/timetable/192970?start=2026-06-01&type=1"
      },
      {
        "id": "moscow-rut-miit__w1_6ffc70c356f5",
        "date": "",
        "weekday": "Понедельник",
        "weekdayNumber": 1,
        "time": "15:20 — 16:40",
        "startTime": "15:20",
        "endTime": "16:40",
        "kind": "Лекция",
        "category": "lesson",
        "subject": "Оборудование машиностроительных производств",
        "teacher": "Комаров Юрий Юрьевич",
        "room": "2126-2",
        "address": "",
        "groups": [],
        "subgroup": "",
        "note": "Лк",
        "isOnline": false,
        "onlineUrl": "",
        "sourceType": 1,
        "sourceUrl": "https://www.miit.ru/timetable/192970?start=2026-06-01&type=1"
      },
      {
        "id": "moscow-rut-miit__w1_5097a84746d1",
        "date": "",
        "weekday": "Понедельник",
        "weekdayNumber": 1,
        "time": "15:20 — 16:40",
        "startTime": "15:20",
        "endTime": "16:40",
        "kind": "Лекция",
        "category": "lesson",
        "subject": "Технология машиностроения",
        "teacher": "Фоля Татьяна Ивановна",
        "room": "2126-2",
        "address": "",
        "groups": [],
        "subgroup": "",
        "note": "Лк",
        "isOnline": false,
        "onlineUrl": "",
        "sourceType": 1,
        "sourceUrl": "https://www.miit.ru/timetable/192970?start=2026-06-01&type=1"
      },
      {
        "id": "moscow-rut-miit__w1_8464efd362b0",
        "date": "",
        "weekday": "Понедельник",
        "weekdayNumber": 1,
        "time": "16:55 — 18:15",
        "startTime": "16:55",
        "endTime": "18:15",
        "kind": "Лекция",
        "category": "lesson",
        "subject": "Оборудование машиностроительных производств",
        "teacher": "Комаров Юрий Юрьевич",
        "room": "2126-2",
        "address": "",
        "groups": [],
        "subgroup": "",
        "note": "Лк",
        "isOnline": false,
        "onlineUrl": "",
        "sourceType": 1,
        "sourceUrl": "https://www.miit.ru/timetable/192970?start=2026-06-01&type=1"
      },
      {
        "id": "moscow-rut-miit__w1_b68d903a40c1",
        "date": "",
        "weekday": "Понедельник",
        "weekdayNumber": 1,
        "time": "16:55 — 18:15",
        "startTime": "16:55",
        "endTime": "18:15",
        "kind": "Практическое занятие",
        "category": "lesson",
        "subject": "Технология машиностроения",
        "teacher": "Фоля Татьяна Ивановна",
        "room": "2126-2",
        "address": "",
        "groups": [],
        "subgroup": "",
        "note": "ПЗ",
        "isOnline": false,
        "onlineUrl": "",
        "sourceType": 1,
        "sourceUrl": "https://www.miit.ru/timetable/192970?start=2026-06-01&type=1"
      },
      {
        "id": "moscow-rut-miit__w1_5b7db1232c9c",
        "date": "",
        "weekday": "Понедельник",
        "weekdayNumber": 1,
        "time": "18:30 — 19:50",
        "startTime": "18:30",
        "endTime": "19:50",
        "kind": "Лекция",
        "category": "lesson",
        "subject": "Оборудование машиностроительных производств",
        "teacher": "Комаров Юрий Юрьевич",
        "room": "2126-2",
        "address": "",
        "groups": [],
        "subgroup": "",
        "note": "Лк",
        "isOnline": false,
        "onlineUrl": "",
        "sourceType": 1,
        "sourceUrl": "https://www.miit.ru/timetable/192970?start=2026-06-01&type=1"
      },
      {
        "id": "moscow-rut-miit__w1_2c99c49af3e8",
        "date": "",
        "weekday": "Понедельник",
        "weekdayNumber": 1,
        "time": "18:30 — 19:50",
        "startTime": "18:30",
        "endTime": "19:50",
        "kind": "Практическое занятие",
        "category": "lesson",
        "subject": "Технология машиностроения",
        "teacher": "Фоля Татьяна Ивановна",
        "room": "2126-2",
        "address": "",
        "groups": [],
        "subgroup": "",
        "note": "ПЗ",
        "isOnline": false,
        "onlineUrl": "",
        "sourceType": 1,
        "sourceUrl": "https://www.miit.ru/timetable/192970?start=2026-06-01&type=1"
      },
      {
        "id": "moscow-rut-miit__w1_a5f988f0ddd1",
        "date": "",
        "weekday": "Понедельник",
        "weekdayNumber": 1,
        "time": "20:00 — 21:20",
        "startTime": "20:00",
        "endTime": "21:20",
        "kind": "Лекция",
        "category": "lesson",
        "subject": "Оборудование машиностроительных производств",
        "teacher": "Комаров Юрий Юрьевич",
        "room": "2126-2",
        "address": "",
        "groups": [],
        "subgroup": "",
        "note": "Лк",
        "isOnline": false,
        "onlineUrl": "",
        "sourceType": 1,
        "sourceUrl": "https://www.miit.ru/timetable/192970?start=2026-06-01&type=1"
      },
      {
        "id": "moscow-rut-miit__w2_1d8a0fe605f6",
        "date": "",
        "weekday": "Вторник",
        "weekdayNumber": 2,
        "time": "13:45 — 15:05",
        "startTime": "13:45",
        "endTime": "15:05",
        "kind": "Лекция",
        "category": "lesson",
        "subject": "Оборудование машиностроительных производств",
        "teacher": "Комаров Юрий Юрьевич",
        "room": "2126-2",
        "address": "",
        "groups": [],
        "subgroup": "",
        "note": "Лк",
        "isOnline": false,
        "onlineUrl": "",
        "sourceType": 1,
        "sourceUrl": "https://www.miit.ru/timetable/192970?start=2026-06-01&type=1"
      },
      {
        "id": "moscow-rut-miit__w2_5de5b8d862c9",
        "date": "",
        "weekday": "Вторник",
        "weekdayNumber": 2,
        "time": "13:45 — 15:05",
        "startTime": "13:45",
        "endTime": "15:05",
        "kind": "Практическое занятие",
        "category": "lesson",
        "subject": "Технология машиностроения",
        "teacher": "Фоля Татьяна Ивановна",
        "room": "2126-2",
        "address": "",
        "groups": [],
        "subgroup": "",
        "note": "ПЗ",
        "isOnline": false,
        "onlineUrl": "",
        "sourceType": 1,
        "sourceUrl": "https://www.miit.ru/timetable/192970?start=2026-06-01&type=1"
      },
      {
        "id": "moscow-rut-miit__w2_6009aa76c80d",
        "date": "",
        "weekday": "Вторник",
        "weekdayNumber": 2,
        "time": "15:20 — 16:40",
        "startTime": "15:20",
        "endTime": "16:40",
        "kind": "Лекция",
        "category": "lesson",
        "subject": "Оборудование машиностроительных производств",
        "teacher": "Комаров Юрий Юрьевич",
        "room": "2126-2",
        "address": "",
        "groups": [],
        "subgroup": "",
        "note": "Лк",
        "isOnline": false,
        "onlineUrl": "",
        "sourceType": 1,
        "sourceUrl": "https://www.miit.ru/timetable/192970?start=2026-06-01&type=1"
      },
      {
        "id": "moscow-rut-miit__w2_a4a721ef5037",
        "date": "",
        "weekday": "Вторник",
        "weekdayNumber": 2,
        "time": "15:20 — 16:40",
        "startTime": "15:20",
        "endTime": "16:40",
        "kind": "Практическое занятие",
        "category": "lesson",
        "subject": "Технология машиностроения",
        "teacher": "Фоля Татьяна Ивановна",
        "room": "2126-2",
        "address": "",
        "groups": [],
        "subgroup": "",
        "note": "ПЗ",
        "isOnline": false,
        "onlineUrl": "",
        "sourceType": 1,
        "sourceUrl": "https://www.miit.ru/timetable/192970?start=2026-06-01&type=1"
      },
      {
        "id": "moscow-rut-miit__w2_8354437f355d",
        "date": "",
        "weekday": "Вторник",
        "weekdayNumber": 2,
        "time": "16:55 — 18:15",
        "startTime": "16:55",
        "endTime": "18:15",
        "kind": "Лекция",
        "category": "lesson",
        "subject": "Оборудование машиностроительных производств",
        "teacher": "Комаров Юрий Юрьевич",
        "room": "2126-2",
        "address": "",
        "groups": [],
        "subgroup": "",
        "note": "Лк",
        "isOnline": false,
        "onlineUrl": "",
        "sourceType": 1,
        "sourceUrl": "https://www.miit.ru/timetable/192970?start=2026-06-01&type=1"
      },
      {
        "id": "moscow-rut-miit__w2_d88a248c4c3d",
        "date": "",
        "weekday": "Вторник",
        "weekdayNumber": 2,
        "time": "16:55 — 18:15",
        "startTime": "16:55",
        "endTime": "18:15",
        "kind": "Практическое занятие",
        "category": "lesson",
        "subject": "Технология машиностроения",
        "teacher": "Фоля Татьяна Ивановна",
        "room": "2126-2",
        "address": "",
        "groups": [],
        "subgroup": "",
        "note": "ПЗ",
        "isOnline": false,
        "onlineUrl": "",
        "sourceType": 1,
        "sourceUrl": "https://www.miit.ru/timetable/192970?start=2026-06-01&type=1"
      },
      {
        "id": "moscow-rut-miit__w2_73a785ed14f6",
        "date": "",
        "weekday": "Вторник",
        "weekdayNumber": 2,
        "time": "18:30 — 19:50",
        "startTime": "18:30",
        "endTime": "19:50",
        "kind": "Лекция",
        "category": "lesson",
        "subject": "Оборудование машиностроительных производств",
        "teacher": "Комаров Юрий Юрьевич",
        "room": "2126-2",
        "address": "",
        "groups": [],
        "subgroup": "",
        "note": "Лк",
        "isOnline": false,
        "onlineUrl": "",
        "sourceType": 1,
        "sourceUrl": "https://www.miit.ru/timetable/192970?start=2026-06-01&type=1"
      },
      {
        "id": "moscow-rut-miit__w2_fece0078c98c",
        "date": "",
        "weekday": "Вторник",
        "weekdayNumber": 2,
        "time": "18:30 — 19:50",
        "startTime": "18:30",
        "endTime": "19:50",
        "kind": "Практическое занятие",
        "category": "lesson",
        "subject": "Технология машиностроения",
        "teacher": "Фоля Татьяна Ивановна",
        "room": "2126-2",
        "address": "",
        "groups": [],
        "subgroup": "",
        "note": "ПЗ",
        "isOnline": false,
        "onlineUrl": "",
        "sourceType": 1,
        "sourceUrl": "https://www.miit.ru/timetable/192970?start=2026-06-01&type=1"
      },
      {
        "id": "moscow-rut-miit__w2_88bcb2f0c1ef",
        "date": "",
        "weekday": "Вторник",
        "weekdayNumber": 2,
        "time": "20:00 — 21:20",
        "startTime": "20:00",
        "endTime": "21:20",
        "kind": "Лекция",
        "category": "lesson",
        "subject": "Оборудование машиностроительных производств",
        "teacher": "Комаров Юрий Юрьевич",
        "room": "2126-2",
        "address": "",
        "groups": [],
        "subgroup": "",
        "note": "Лк",
        "isOnline": false,
        "onlineUrl": "",
        "sourceType": 1,
        "sourceUrl": "https://www.miit.ru/timetable/192970?start=2026-06-01&type=1"
      },
      {
        "id": "moscow-rut-miit__w3_48a8c0776903",
        "date": "",
        "weekday": "Среда",
        "weekdayNumber": 3,
        "time": "13:45 — 15:05",
        "startTime": "13:45",
        "endTime": "15:05",
        "kind": "Лекция",
        "category": "lesson",
        "subject": "Управление станками и станочными комплексами",
        "teacher": "Попова Татьяна Александровна",
        "room": "2126-2",
        "address": "",
        "groups": [],
        "subgroup": "",
        "note": "Лк",
        "isOnline": false,
        "onlineUrl": "",
        "sourceType": 1,
        "sourceUrl": "https://www.miit.ru/timetable/192970?start=2026-06-01&type=1"
      },
      {
        "id": "moscow-rut-miit__w3_8e77e1d74a9c",
        "date": "",
        "weekday": "Среда",
        "weekdayNumber": 3,
        "time": "15:20 — 16:40",
        "startTime": "15:20",
        "endTime": "16:40",
        "kind": "Лекция",
        "category": "lesson",
        "subject": "Управление станками и станочными комплексами",
        "teacher": "Попова Татьяна Александровна",
        "room": "2126-2",
        "address": "",
        "groups": [],
        "subgroup": "",
        "note": "Лк",
        "isOnline": false,
        "onlineUrl": "",
        "sourceType": 1,
        "sourceUrl": "https://www.miit.ru/timetable/192970?start=2026-06-01&type=1"
      },
      {
        "id": "moscow-rut-miit__w3_117d3137f1e2",
        "date": "",
        "weekday": "Среда",
        "weekdayNumber": 3,
        "time": "16:55 — 18:15",
        "startTime": "16:55",
        "endTime": "18:15",
        "kind": "Лабораторная работа",
        "category": "lesson",
        "subject": "Оборудование машиностроительных производств",
        "teacher": "Комаров Юрий Юрьевич",
        "room": "2126-2",
        "address": "",
        "groups": [],
        "subgroup": "",
        "note": "ЛР",
        "isOnline": false,
        "onlineUrl": "",
        "sourceType": 1,
        "sourceUrl": "https://www.miit.ru/timetable/192970?start=2026-06-01&type=1"
      },
      {
        "id": "moscow-rut-miit__w3_60bc561dfb45",
        "date": "",
        "weekday": "Среда",
        "weekdayNumber": 3,
        "time": "16:55 — 18:15",
        "startTime": "16:55",
        "endTime": "18:15",
        "kind": "Лекция",
        "category": "lesson",
        "subject": "Управление станками и станочными комплексами",
        "teacher": "Попова Татьяна Александровна",
        "room": "2126-2",
        "address": "",
        "groups": [],
        "subgroup": "",
        "note": "Лк",
        "isOnline": false,
        "onlineUrl": "",
        "sourceType": 1,
        "sourceUrl": "https://www.miit.ru/timetable/192970?start=2026-06-01&type=1"
      },
      {
        "id": "moscow-rut-miit__w3_42457cfa5490",
        "date": "",
        "weekday": "Среда",
        "weekdayNumber": 3,
        "time": "18:30 — 19:50",
        "startTime": "18:30",
        "endTime": "19:50",
        "kind": "Лабораторная работа",
        "category": "lesson",
        "subject": "Оборудование машиностроительных производств",
        "teacher": "Комаров Юрий Юрьевич",
        "room": "2126-2",
        "address": "",
        "groups": [],
        "subgroup": "",
        "note": "ЛР",
        "isOnline": false,
        "onlineUrl": "",
        "sourceType": 1,
        "sourceUrl": "https://www.miit.ru/timetable/192970?start=2026-06-01&type=1"
      },
      {
        "id": "moscow-rut-miit__w3_620998ee5378",
        "date": "",
        "weekday": "Среда",
        "weekdayNumber": 3,
        "time": "18:30 — 19:50",
        "startTime": "18:30",
        "endTime": "19:50",
        "kind": "Лекция",
        "category": "lesson",
        "subject": "Управление станками и станочными комплексами",
        "teacher": "Попова Татьяна Александровна",
        "room": "2126-2",
        "address": "",
        "groups": [],
        "subgroup": "",
        "note": "Лк",
        "isOnline": false,
        "onlineUrl": "",
        "sourceType": 1,
        "sourceUrl": "https://www.miit.ru/timetable/192970?start=2026-06-01&type=1"
      },
      {
        "id": "moscow-rut-miit__w3_1a17abbf093c",
        "date": "",
        "weekday": "Среда",
        "weekdayNumber": 3,
        "time": "20:00 — 21:20",
        "startTime": "20:00",
        "endTime": "21:20",
        "kind": "Лабораторная работа",
        "category": "lesson",
        "subject": "Оборудование машиностроительных производств",
        "teacher": "Комаров Юрий Юрьевич",
        "room": "2126-2",
        "address": "",
        "groups": [],
        "subgroup": "",
        "note": "ЛР",
        "isOnline": false,
        "onlineUrl": "",
        "sourceType": 1,
        "sourceUrl": "https://www.miit.ru/timetable/192970?start=2026-06-01&type=1"
      },
      {
        "id": "moscow-rut-miit__w3_d38726325d7f",
        "date": "",
        "weekday": "Среда",
        "weekdayNumber": 3,
        "time": "20:00 — 21:20",
        "startTime": "20:00",
        "endTime": "21:20",
        "kind": "Лекция",
        "category": "lesson",
        "subject": "Управление станками и станочными комплексами",
        "teacher": "Попова Татьяна Александровна",
        "room": "2126-2",
        "address": "",
        "groups": [],
        "subgroup": "",
        "note": "Лк",
        "isOnline": false,
        "onlineUrl": "",
        "sourceType": 1,
        "sourceUrl": "https://www.miit.ru/timetable/192970?start=2026-06-01&type=1"
      },
      {
        "id": "moscow-rut-miit__w4_e26529c7fb43",
        "date": "",
        "weekday": "Четверг",
        "weekdayNumber": 4,
        "time": "13:45 — 15:05",
        "startTime": "13:45",
        "endTime": "15:05",
        "kind": "Практическое занятие",
        "category": "lesson",
        "subject": "Оборудование машиностроительных производств",
        "teacher": "Комаров Юрий Юрьевич",
        "room": "2126-2",
        "address": "",
        "groups": [],
        "subgroup": "",
        "note": "ПЗ",
        "isOnline": false,
        "onlineUrl": "",
        "sourceType": 1,
        "sourceUrl": "https://www.miit.ru/timetable/192970?start=2026-06-01&type=1"
      },
      {
        "id": "moscow-rut-miit__w4_49c1ed732e41",
        "date": "",
        "weekday": "Четверг",
        "weekdayNumber": 4,
        "time": "13:45 — 15:05",
        "startTime": "13:45",
        "endTime": "15:05",
        "kind": "Лекция",
        "category": "lesson",
        "subject": "Управление станками и станочными комплексами",
        "teacher": "Попова Татьяна Александровна",
        "room": "2126-2",
        "address": "",
        "groups": [],
        "subgroup": "",
        "note": "Лк",
        "isOnline": false,
        "onlineUrl": "",
        "sourceType": 1,
        "sourceUrl": "https://www.miit.ru/timetable/192970?start=2026-06-01&type=1"
      },
      {
        "id": "moscow-rut-miit__w4_edb29c587eca",
        "date": "",
        "weekday": "Четверг",
        "weekdayNumber": 4,
        "time": "15:20 — 16:40",
        "startTime": "15:20",
        "endTime": "16:40",
        "kind": "Практическое занятие",
        "category": "lesson",
        "subject": "Оборудование машиностроительных производств",
        "teacher": "Комаров Юрий Юрьевич",
        "room": "2126-2",
        "address": "",
        "groups": [],
        "subgroup": "",
        "note": "ПЗ",
        "isOnline": false,
        "onlineUrl": "",
        "sourceType": 1,
        "sourceUrl": "https://www.miit.ru/timetable/192970?start=2026-06-01&type=1"
      },
      {
        "id": "moscow-rut-miit__w4_164215ce303e",
        "date": "",
        "weekday": "Четверг",
        "weekdayNumber": 4,
        "time": "15:20 — 16:40",
        "startTime": "15:20",
        "endTime": "16:40",
        "kind": "Лекция",
        "category": "lesson",
        "subject": "Управление станками и станочными комплексами",
        "teacher": "Попова Татьяна Александровна",
        "room": "2126-2",
        "address": "",
        "groups": [],
        "subgroup": "",
        "note": "Лк",
        "isOnline": false,
        "onlineUrl": "",
        "sourceType": 1,
        "sourceUrl": "https://www.miit.ru/timetable/192970?start=2026-06-01&type=1"
      },
      {
        "id": "moscow-rut-miit__w4_99a1e9aa0532",
        "date": "",
        "weekday": "Четверг",
        "weekdayNumber": 4,
        "time": "16:55 — 18:15",
        "startTime": "16:55",
        "endTime": "18:15",
        "kind": "Практическое занятие",
        "category": "lesson",
        "subject": "Оборудование машиностроительных производств",
        "teacher": "Комаров Юрий Юрьевич",
        "room": "2126-2",
        "address": "",
        "groups": [],
        "subgroup": "",
        "note": "ПЗ",
        "isOnline": false,
        "onlineUrl": "",
        "sourceType": 1,
        "sourceUrl": "https://www.miit.ru/timetable/192970?start=2026-06-01&type=1"
      },
      {
        "id": "moscow-rut-miit__w4_14d53a362384",
        "date": "",
        "weekday": "Четверг",
        "weekdayNumber": 4,
        "time": "16:55 — 18:15",
        "startTime": "16:55",
        "endTime": "18:15",
        "kind": "Практическое занятие",
        "category": "lesson",
        "subject": "Управление станками и станочными комплексами",
        "teacher": "Попова Татьяна Александровна",
        "room": "2126-2",
        "address": "",
        "groups": [],
        "subgroup": "",
        "note": "ПЗ",
        "isOnline": false,
        "onlineUrl": "",
        "sourceType": 1,
        "sourceUrl": "https://www.miit.ru/timetable/192970?start=2026-06-01&type=1"
      },
      {
        "id": "moscow-rut-miit__w4_bdb28813f418",
        "date": "",
        "weekday": "Четверг",
        "weekdayNumber": 4,
        "time": "18:30 — 19:50",
        "startTime": "18:30",
        "endTime": "19:50",
        "kind": "Практическое занятие",
        "category": "lesson",
        "subject": "Оборудование машиностроительных производств",
        "teacher": "Комаров Юрий Юрьевич",
        "room": "2126-2",
        "address": "",
        "groups": [],
        "subgroup": "",
        "note": "ПЗ",
        "isOnline": false,
        "onlineUrl": "",
        "sourceType": 1,
        "sourceUrl": "https://www.miit.ru/timetable/192970?start=2026-06-01&type=1"
      },
      {
        "id": "moscow-rut-miit__w4_8da6f1a2860a",
        "date": "",
        "weekday": "Четверг",
        "weekdayNumber": 4,
        "time": "18:30 — 19:50",
        "startTime": "18:30",
        "endTime": "19:50",
        "kind": "Практическое занятие",
        "category": "lesson",
        "subject": "Управление станками и станочными комплексами",
        "teacher": "Попова Татьяна Александровна",
        "room": "2126-2",
        "address": "",
        "groups": [],
        "subgroup": "",
        "note": "ПЗ",
        "isOnline": false,
        "onlineUrl": "",
        "sourceType": 1,
        "sourceUrl": "https://www.miit.ru/timetable/192970?start=2026-06-01&type=1"
      },
      {
        "id": "moscow-rut-miit__w4_5c640699356c",
        "date": "",
        "weekday": "Четверг",
        "weekdayNumber": 4,
        "time": "20:00 — 21:20",
        "startTime": "20:00",
        "endTime": "21:20",
        "kind": "Практическое занятие",
        "category": "lesson",
        "subject": "Оборудование машиностроительных производств",
        "teacher": "Комаров Юрий Юрьевич",
        "room": "2126-2",
        "address": "",
        "groups": [],
        "subgroup": "",
        "note": "ПЗ",
        "isOnline": false,
        "onlineUrl": "",
        "sourceType": 1,
        "sourceUrl": "https://www.miit.ru/timetable/192970?start=2026-06-01&type=1"
      },
      {
        "id": "moscow-rut-miit__w4_f6443e66a45a",
        "date": "",
        "weekday": "Четверг",
        "weekdayNumber": 4,
        "time": "20:00 — 21:20",
        "startTime": "20:00",
        "endTime": "21:20",
        "kind": "Практическое занятие",
        "category": "lesson",
        "subject": "Управление станками и станочными комплексами",
        "teacher": "Попова Татьяна Александровна",
        "room": "2126-2",
        "address": "",
        "groups": [],
        "subgroup": "",
        "note": "ПЗ",
        "isOnline": false,
        "onlineUrl": "",
        "sourceType": 1,
        "sourceUrl": "https://www.miit.ru/timetable/192970?start=2026-06-01&type=1"
      },
      {
        "id": "moscow-rut-miit__w5_e17c0f851534",
        "date": "",
        "weekday": "Пятница",
        "weekdayNumber": 5,
        "time": "13:45 — 15:05",
        "startTime": "13:45",
        "endTime": "15:05",
        "kind": "Практическое занятие",
        "category": "lesson",
        "subject": "Оборудование машиностроительных производств",
        "teacher": "Комаров Юрий Юрьевич",
        "room": "2126-2",
        "address": "",
        "groups": [],
        "subgroup": "",
        "note": "ПЗ",
        "isOnline": false,
        "onlineUrl": "",
        "sourceType": 1,
        "sourceUrl": "https://www.miit.ru/timetable/192970?start=2026-06-01&type=1"
      },
      {
        "id": "moscow-rut-miit__w5_32ff4f57b203",
        "date": "",
        "weekday": "Пятница",
        "weekdayNumber": 5,
        "time": "15:20 — 16:40",
        "startTime": "15:20",
        "endTime": "16:40",
        "kind": "Практическое занятие",
        "category": "lesson",
        "subject": "Оборудование машиностроительных производств",
        "teacher": "Комаров Юрий Юрьевич",
        "room": "2126-2",
        "address": "",
        "groups": [],
        "subgroup": "",
        "note": "ПЗ",
        "isOnline": false,
        "onlineUrl": "",
        "sourceType": 1,
        "sourceUrl": "https://www.miit.ru/timetable/192970?start=2026-06-01&type=1"
      },
      {
        "id": "moscow-rut-miit__w5_659f108d696d",
        "date": "",
        "weekday": "Пятница",
        "weekdayNumber": 5,
        "time": "16:55 — 18:15",
        "startTime": "16:55",
        "endTime": "18:15",
        "kind": "Практическое занятие",
        "category": "lesson",
        "subject": "Оборудование машиностроительных производств",
        "teacher": "Комаров Юрий Юрьевич",
        "room": "2126-2",
        "address": "",
        "groups": [],
        "subgroup": "",
        "note": "ПЗ",
        "isOnline": false,
        "onlineUrl": "",
        "sourceType": 1,
        "sourceUrl": "https://www.miit.ru/timetable/192970?start=2026-06-01&type=1"
      },
      {
        "id": "moscow-rut-miit__w5_f87e7ce68cdf",
        "date": "",
        "weekday": "Пятница",
        "weekdayNumber": 5,
        "time": "18:30 — 19:50",
        "startTime": "18:30",
        "endTime": "19:50",
        "kind": "Практическое занятие",
        "category": "lesson",
        "subject": "Оборудование машиностроительных производств",
        "teacher": "Комаров Юрий Юрьевич",
        "room": "2126-2",
        "address": "",
        "groups": [],
        "subgroup": "",
        "note": "ПЗ",
        "isOnline": false,
        "onlineUrl": "",
        "sourceType": 1,
        "sourceUrl": "https://www.miit.ru/timetable/192970?start=2026-06-01&type=1"
      },
      {
        "id": "moscow-rut-miit__w5_ccfc2abfaf58",
        "date": "",
        "weekday": "Пятница",
        "weekdayNumber": 5,
        "time": "20:00 — 21:20",
        "startTime": "20:00",
        "endTime": "21:20",
        "kind": "Практическое занятие",
        "category": "lesson",
        "subject": "Оборудование машиностроительных производств",
        "teacher": "Комаров Юрий Юрьевич",
        "room": "2126-2",
        "address": "",
        "groups": [],
        "subgroup": "",
        "note": "ПЗ",
        "isOnline": false,
        "onlineUrl": "",
        "sourceType": 1,
        "sourceUrl": "https://www.miit.ru/timetable/192970?start=2026-06-01&type=1"
      }
    ]
  },
  "exceptions": [],
  "meta": {
    "source": "miit.ru",
    "parserVersion": "3.2-js-smart-safe",
    "timezone": "Europe/Moscow",
    "errors": []
  }
}