{
  "university": "РУТ (МИИТ)",
  "group": "ШЦТ-211",
  "updatedAt": "2026-06-11T02:25:49+03:00",
  "events": [
    {
      "date": "2026-06-18",
      "weekday": "Четверг",
      "time": "09:00 — 10:00",
      "kind": "Консультация",
      "subject": "Коммерческая работа",
      "teacher": "Подорожкина А.В",
      "room": "8411",
      "isPast": false
    },
    {
      "date": "2026-06-19",
      "weekday": "Пятница",
      "time": "10:00 — 15:00",
      "kind": "Экзамен",
      "subject": "Коммерческая работа",
      "teacher": "Подорожкина А.В",
      "room": "8411",
      "isPast": false
    },
    {
      "date": "2026-06-22",
      "weekday": "Понедельник",
      "time": "09:00 — 10:00",
      "kind": "Консультация",
      "subject": "История России",
      "teacher": "Кочетков Е.Е",
      "room": "8410",
      "isPast": false
    },
    {
      "date": "2026-06-23",
      "weekday": "Вторник",
      "time": "10:00 — 15:00",
      "kind": "Экзамен",
      "subject": "История России",
      "teacher": "Кочетков Е.Е",
      "room": "8410",
      "isPast": false
    },
    {
      "date": "2026-06-26",
      "weekday": "Пятница",
      "time": "09:00 — 10:00",
      "kind": "Консультация",
      "subject": "Разработка цифровых решений на базе технологий 1С",
      "teacher": "Бадави Д.Т",
      "room": "8507",
      "isPast": false
    },
    {
      "date": "2026-06-27",
      "weekday": "Суббота",
      "time": "10:00 — 15:00",
      "kind": "Экзамен",
      "subject": "Разработка цифровых решений на базе технологий 1С",
      "teacher": "Бадави Д.Т",
      "room": "8507",
      "isPast": false
    }
  ]
}